{"is_source_file": false, "format": "", "description": "", "external_files": [], "external_methods": [], "published": [], "classes": [], "methods": [], "calls": [], "search-terms": [], "state": 2, "file_id": 3, "knowledge_revision": 28, "git_revision": "022d3fb5d774ab6b8492e51673b62d1779d4dfd5", "hash": "d250fc792289b6782c9f2c860ce9a36b", "format-version": 4, "code-base-name": "frontend_react", "filename": "frontend_react/src/index.css", "revision_history": [{"28": "022d3fb5d774ab6b8492e51673b62d1779d4dfd5"}]}